miniseqtoolbox/__init__.py
miniseqtoolbox/my_bio_module.py
miniseqtoolbox-1.1.7.dist-info/METADATA
miniseqtoolbox-1.1.7.dist-info/WHEEL
miniseqtoolbox-1.1.7.dist-info/top_level.txt
miniseqtoolbox-1.1.7.dist-info/RECORD
