Metadata-Version: 2.1
Name: miniseqtoolbox
Version: 1.1.7
Summary: A mini toolbox for moleuclar sequence analysis
Home-page: UNKNOWN
Author: YuanLi
Author-email: <ivon19571226@gmail.com>
License: UNKNOWN
Keywords: python,miniseqtoolbox
Platform: UNKNOWN
Classifier: Development Status :: 3 - Alpha
Classifier: Intended Audience :: Education
Classifier: Programming Language :: Python :: 3
Classifier: Operating System :: MacOS :: MacOS X
Classifier: Operating System :: Microsoft :: Windows
